<?xml version="1.0" encoding="UTF-8"?>
<struct>
    <LoW>800</LoW>
    <LoW>750</LoW>
    <LoW>700</LoW>
    <LoW>600</LoW>
    <LoW>750</LoW>
    <PBQ>5</PBQ>
    <PBQ>5</PBQ>
    <PBQ>1</PBQ>
    <PBQ>5</PBQ>
    <PBQ>3</PBQ>
    <PBQ>1</PBQ>
    <PBQ>2</PBQ>
    <PBQ>3</PBQ>
    <PBQ>5</PBQ>
    <PBQ>5</PBQ>
    <PBQ>1</PBQ>
    <PBQ>5</PBQ>
    <PBQ>5</PBQ>
    <PBQ>3</PBQ>
    <PBQ>4</PBQ>
    <PBQ>1</PBQ>
    <PBQ>2</PBQ>
    <PBQ>5</PBQ>
    <PBQ>4</PBQ>
    <PBQ>5</PBQ>
    <PBQ>4</PBQ>
    <PBQ>1</PBQ>
    <PBQ>5</PBQ>
    <PBQ>5</PBQ>
    <PBQ>4</PBQ>
    <PBQ>4</PBQ>
    <PBQ>4</PBQ>
    <PBQ>2</PBQ>
    <PBQ>4</PBQ>
    <PBQ>1</PBQ>
    <PBQ>4</PBQ>
    <PBQ>1</PBQ>
    <PBQ>2</PBQ>
    <PBQ>1</PBQ>
    <PBQ>1</PBQ>
    <PBQ>5</PBQ>
    <PBQ>4</PBQ>
    <PBQ>2</PBQ>
    <PBQ>5</PBQ>
    <PBQ>1</PBQ>
    <PBQ>2</PBQ>
    <PBQ>2</PBQ>
    <PBQ>4</PBQ>
    <PBQ>4</PBQ>
    <PBQ>1</PBQ>
    <PBQ>3</PBQ>
    <PBQ>3</PBQ>
    <PBQ>3</PBQ>
    <PBQ>4</PBQ>
    <PBQ>4</PBQ>
    <PBQ>2</PBQ>
    <PBQ>4</PBQ>
    <PBQ>4</PBQ>
    <PBQ>1</PBQ>
    <PBQ>1</PBQ>
    <PBQ>3</PBQ>
    <PBQ>5</PBQ>
    <PBQ>2</PBQ>
    <PBQ>3</PBQ>
    <PBQ>2</PBQ>
    <PBQ>4</PBQ>
    <PBQ>2</PBQ>
    <PBQ>3</PBQ>
    <PBQ>4</PBQ>
    <PBQ>5</PBQ>
    <PBQ>5</PBQ>
    <PBQ>3</PBQ>
    <PBQ>1</PBQ>
    <PBQ>1</PBQ>
    <PBQ>2</PBQ>
    <PBQ>5</PBQ>
    <PBQ>2</PBQ>
    <PBQ>4</PBQ>
    <PBQ>2</PBQ>
    <PBQ>5</PBQ>
    <PBQ>2</PBQ>
    <PBQ>2</PBQ>
    <PBQ>2</PBQ>
    <PBQ>3</PBQ>
    <PBQ>3</PBQ>
    <PBQ>2</PBQ>
    <PBQ>5</PBQ>
    <PBQ>3</PBQ>
    <PBQ>3</PBQ>
    <PBQ>5</PBQ>
    <PBQ>2</PBQ>
    <PBQ>4</PBQ>
    <PBQ>4</PBQ>
    <PBQ>2</PBQ>
    <PBQ>3</PBQ>
    <PBQ>1</PBQ>
    <PBQ>1</PBQ>
    <PBQ>3</PBQ>
    <PBQ>4</PBQ>
    <PBQ>5</PBQ>
    <PBQ>1</PBQ>
    <PBQ>3</PBQ>
    <PBQ>3</PBQ>
    <PBQ>1</PBQ>
    <PBQ>2</PBQ>
    <PBQ>1</PBQ>
    <PBQ>4</PBQ>
    <PBQ>2</PBQ>
    <PBQ>3</PBQ>
    <PBQ>1</PBQ>
    <PBQ>3</PBQ>
    <PBQ>2</PBQ>
    <PBQ>3</PBQ>
    <PBQ>4</PBQ>
    <PBQ>4</PBQ>
    <PBQ>3</PBQ>
    <PBQ>1</PBQ>
    <PBQ>2</PBQ>
    <PBQ>5</PBQ>
    <PBQ>1</PBQ>
    <PBQ>5</PBQ>
    <PBQ>3</PBQ>
    <PBQ>5</PBQ>
    <PBQ>1</PBQ>
    <PBQ>3</PBQ>
    <Vessels_>1</Vessels_>
    <Vessels_>2</Vessels_>
    <Vessels_>3</Vessels_>
    <Vessels_>4</Vessels_>
    <Vessels_>5</Vessels_>
    <Vessels_>6</Vessels_>
    <Vessels_>7</Vessels_>
    <Vessels_>8</Vessels_>
    <Vessels_>9</Vessels_>
    <Vessels_>10</Vessels_>
    <Vessels_>11</Vessels_>
    <Vessels_>12</Vessels_>
    <Vessels_>13</Vessels_>
    <Vessels_>14</Vessels_>
    <Vessels_>15</Vessels_>
    <Vessels_>16</Vessels_>
    <Vessels_>17</Vessels_>
    <Vessels_>18</Vessels_>
    <Vessels_>19</Vessels_>
    <Vessels_>20</Vessels_>
    <Vessels_>21</Vessels_>
    <Vessels_>22</Vessels_>
    <Vessels_>23</Vessels_>
    <Vessels_>24</Vessels_>
    <Vessels_>25</Vessels_>
    <Vessels_>26</Vessels_>
    <Vessels_>27</Vessels_>
    <Vessels_>28</Vessels_>
    <Vessels_>29</Vessels_>
    <Vessels_>30</Vessels_>
    <Vessels_>31</Vessels_>
    <Vessels_>32</Vessels_>
    <Vessels_>33</Vessels_>
    <Vessels_>34</Vessels_>
    <Vessels_>35</Vessels_>
    <Vessels_>36</Vessels_>
    <Vessels_>37</Vessels_>
    <Vessels_>38</Vessels_>
    <Vessels_>39</Vessels_>
    <Vessels_>40</Vessels_>
    <Vessels_>41</Vessels_>
    <Vessels_>42</Vessels_>
    <Vessels_>43</Vessels_>
    <Vessels_>44</Vessels_>
    <Vessels_>45</Vessels_>
    <Vessels_>46</Vessels_>
    <Vessels_>47</Vessels_>
    <Vessels_>48</Vessels_>
    <Vessels_>49</Vessels_>
    <Vessels_>50</Vessels_>
    <Vessels_>51</Vessels_>
    <Vessels_>52</Vessels_>
    <Vessels_>53</Vessels_>
    <Vessels_>54</Vessels_>
    <Vessels_>55</Vessels_>
    <Vessels_>56</Vessels_>
    <Vessels_>57</Vessels_>
    <Vessels_>58</Vessels_>
    <Vessels_>59</Vessels_>
    <Vessels_>60</Vessels_>
    <Vessels_>61</Vessels_>
    <Vessels_>62</Vessels_>
    <Vessels_>63</Vessels_>
    <Vessels_>64</Vessels_>
    <Vessels_>65</Vessels_>
    <Vessels_>66</Vessels_>
    <Vessels_>67</Vessels_>
    <Vessels_>68</Vessels_>
    <Vessels_>69</Vessels_>
    <Vessels_>70</Vessels_>
    <Vessels_>71</Vessels_>
    <Vessels_>72</Vessels_>
    <Vessels_>73</Vessels_>
    <Vessels_>74</Vessels_>
    <Vessels_>75</Vessels_>
    <Vessels_>76</Vessels_>
    <Vessels_>77</Vessels_>
    <Vessels_>78</Vessels_>
    <Vessels_>79</Vessels_>
    <Vessels_>80</Vessels_>
    <Vessels_>81</Vessels_>
    <Vessels_>82</Vessels_>
    <Vessels_>83</Vessels_>
    <Vessels_>84</Vessels_>
    <Vessels_>85</Vessels_>
    <Vessels_>86</Vessels_>
    <Vessels_>87</Vessels_>
    <Vessels_>88</Vessels_>
    <Vessels_>89</Vessels_>
    <Vessels_>90</Vessels_>
    <Vessels_>91</Vessels_>
    <Vessels_>92</Vessels_>
    <Vessels_>93</Vessels_>
    <Vessels_>94</Vessels_>
    <Vessels_>95</Vessels_>
    <Vessels_>96</Vessels_>
    <Vessels_>97</Vessels_>
    <Vessels_>98</Vessels_>
    <Vessels_>99</Vessels_>
    <Vessels_>100</Vessels_>
    <Vessels_>101</Vessels_>
    <Vessels_>102</Vessels_>
    <Vessels_>103</Vessels_>
    <Vessels_>104</Vessels_>
    <Vessels_>105</Vessels_>
    <Vessels_>106</Vessels_>
    <Vessels_>107</Vessels_>
    <Vessels_>108</Vessels_>
    <Vessels_>109</Vessels_>
    <Vessels_>110</Vessels_>
    <Vessels_>111</Vessels_>
    <Vessels_>112</Vessels_>
    <Vessels_>113</Vessels_>
    <Vessels_>114</Vessels_>
    <Vessels_>115</Vessels_>
    <Vessels_>116</Vessels_>
    <Vessels_>117</Vessels_>
    <Vessels_>118</Vessels_>
    <Vessels_>119</Vessels_>
    <Vessels_>120</Vessels_>
    <vessellength>119</vessellength>
    <vessellength>90</vessellength>
    <vessellength>83</vessellength>
    <vessellength>77</vessellength>
    <vessellength>73</vessellength>
    <vessellength>72</vessellength>
    <vessellength>115</vessellength>
    <vessellength>90</vessellength>
    <vessellength>73</vessellength>
    <vessellength>78</vessellength>
    <vessellength>85</vessellength>
    <vessellength>101</vessellength>
    <vessellength>92</vessellength>
    <vessellength>174</vessellength>
    <vessellength>117</vessellength>
    <vessellength>85</vessellength>
    <vessellength>78</vessellength>
    <vessellength>79</vessellength>
    <vessellength>90</vessellength>
    <vessellength>75</vessellength>
    <vessellength>83</vessellength>
    <vessellength>99</vessellength>
    <vessellength>81</vessellength>
    <vessellength>120</vessellength>
    <vessellength>83</vessellength>
    <vessellength>103</vessellength>
    <vessellength>113</vessellength>
    <vessellength>94</vessellength>
    <vessellength>145</vessellength>
    <vessellength>78</vessellength>
    <vessellength>104</vessellength>
    <vessellength>177</vessellength>
    <vessellength>155</vessellength>
    <vessellength>76</vessellength>
    <vessellength>90</vessellength>
    <vessellength>92</vessellength>
    <vessellength>80</vessellength>
    <vessellength>107</vessellength>
    <vessellength>120</vessellength>
    <vessellength>103</vessellength>
    <vessellength>98</vessellength>
    <vessellength>120</vessellength>
    <vessellength>91</vessellength>
    <vessellength>99</vessellength>
    <vessellength>198</vessellength>
    <vessellength>185</vessellength>
    <vessellength>85</vessellength>
    <vessellength>94</vessellength>
    <vessellength>86</vessellength>
    <vessellength>119</vessellength>
    <vessellength>91</vessellength>
    <vessellength>96</vessellength>
    <vessellength>118</vessellength>
    <vessellength>73</vessellength>
    <vessellength>109</vessellength>
    <vessellength>70</vessellength>
    <vessellength>110</vessellength>
    <vessellength>77</vessellength>
    <vessellength>116</vessellength>
    <vessellength>99</vessellength>
    <vessellength>104</vessellength>
    <vessellength>76</vessellength>
    <vessellength>87</vessellength>
    <vessellength>101</vessellength>
    <vessellength>76</vessellength>
    <vessellength>103</vessellength>
    <vessellength>75</vessellength>
    <vessellength>108</vessellength>
    <vessellength>77</vessellength>
    <vessellength>133</vessellength>
    <vessellength>77</vessellength>
    <vessellength>92</vessellength>
    <vessellength>105</vessellength>
    <vessellength>80</vessellength>
    <vessellength>90</vessellength>
    <vessellength>118</vessellength>
    <vessellength>78</vessellength>
    <vessellength>77</vessellength>
    <vessellength>86</vessellength>
    <vessellength>95</vessellength>
    <vessellength>143</vessellength>
    <vessellength>199</vessellength>
    <vessellength>94</vessellength>
    <vessellength>113</vessellength>
    <vessellength>101</vessellength>
    <vessellength>99</vessellength>
    <vessellength>133</vessellength>
    <vessellength>101</vessellength>
    <vessellength>80</vessellength>
    <vessellength>97</vessellength>
    <vessellength>95</vessellength>
    <vessellength>102</vessellength>
    <vessellength>77</vessellength>
    <vessellength>165</vessellength>
    <vessellength>182</vessellength>
    <vessellength>71</vessellength>
    <vessellength>103</vessellength>
    <vessellength>92</vessellength>
    <vessellength>85</vessellength>
    <vessellength>91</vessellength>
    <vessellength>88</vessellength>
    <vessellength>116</vessellength>
    <vessellength>107</vessellength>
    <vessellength>80</vessellength>
    <vessellength>70</vessellength>
    <vessellength>75</vessellength>
    <vessellength>72</vessellength>
    <vessellength>109</vessellength>
    <vessellength>84</vessellength>
    <vessellength>96</vessellength>
    <vessellength>98</vessellength>
    <vessellength>107</vessellength>
    <vessellength>174</vessellength>
    <vessellength>118</vessellength>
    <vessellength>102</vessellength>
    <vessellength>81</vessellength>
    <vessellength>88</vessellength>
    <vessellength>74</vessellength>
    <vessellength>102</vessellength>
    <vessellength>82</vessellength>
    <ProcessingTimeOfVessel>3</ProcessingTimeOfVessel>
    <ProcessingTimeOfVessel>4</ProcessingTimeOfVessel>
    <ProcessingTimeOfVessel>3</ProcessingTimeOfVessel>
    <ProcessingTimeOfVessel>7</ProcessingTimeOfVessel>
    <ProcessingTimeOfVessel>4</ProcessingTimeOfVessel>
    <ProcessingTimeOfVessel>7</ProcessingTimeOfVessel>
    <ProcessingTimeOfVessel>4</ProcessingTimeOfVessel>
    <ProcessingTimeOfVessel>3</ProcessingTimeOfVessel>
    <ProcessingTimeOfVessel>4</ProcessingTimeOfVessel>
    <ProcessingTimeOfVessel>6</ProcessingTimeOfVessel>
    <ProcessingTimeOfVessel>6</ProcessingTimeOfVessel>
    <ProcessingTimeOfVessel>6</ProcessingTimeOfVessel>
    <ProcessingTimeOfVessel>5</ProcessingTimeOfVessel>
    <ProcessingTimeOfVessel>6</ProcessingTimeOfVessel>
    <ProcessingTimeOfVessel>7</ProcessingTimeOfVessel>
    <ProcessingTimeOfVessel>5</ProcessingTimeOfVessel>
    <ProcessingTimeOfVessel>4</ProcessingTimeOfVessel>
    <ProcessingTimeOfVessel>7</ProcessingTimeOfVessel>
    <ProcessingTimeOfVessel>5</ProcessingTimeOfVessel>
    <ProcessingTimeOfVessel>4</ProcessingTimeOfVessel>
    <ProcessingTimeOfVessel>7</ProcessingTimeOfVessel>
    <ProcessingTimeOfVessel>4</ProcessingTimeOfVessel>
    <ProcessingTimeOfVessel>5</ProcessingTimeOfVessel>
    <ProcessingTimeOfVessel>3</ProcessingTimeOfVessel>
    <ProcessingTimeOfVessel>4</ProcessingTimeOfVessel>
    <ProcessingTimeOfVessel>5</ProcessingTimeOfVessel>
    <ProcessingTimeOfVessel>6</ProcessingTimeOfVessel>
    <ProcessingTimeOfVessel>7</ProcessingTimeOfVessel>
    <ProcessingTimeOfVessel>3</ProcessingTimeOfVessel>
    <ProcessingTimeOfVessel>7</ProcessingTimeOfVessel>
    <ProcessingTimeOfVessel>3</ProcessingTimeOfVessel>
    <ProcessingTimeOfVessel>6</ProcessingTimeOfVessel>
    <ProcessingTimeOfVessel>7</ProcessingTimeOfVessel>
    <ProcessingTimeOfVessel>3</ProcessingTimeOfVessel>
    <ProcessingTimeOfVessel>5</ProcessingTimeOfVessel>
    <ProcessingTimeOfVessel>3</ProcessingTimeOfVessel>
    <ProcessingTimeOfVessel>5</ProcessingTimeOfVessel>
    <ProcessingTimeOfVessel>4</ProcessingTimeOfVessel>
    <ProcessingTimeOfVessel>4</ProcessingTimeOfVessel>
    <ProcessingTimeOfVessel>3</ProcessingTimeOfVessel>
    <ProcessingTimeOfVessel>7</ProcessingTimeOfVessel>
    <ProcessingTimeOfVessel>3</ProcessingTimeOfVessel>
    <ProcessingTimeOfVessel>5</ProcessingTimeOfVessel>
    <ProcessingTimeOfVessel>4</ProcessingTimeOfVessel>
    <ProcessingTimeOfVessel>6</ProcessingTimeOfVessel>
    <ProcessingTimeOfVessel>7</ProcessingTimeOfVessel>
    <ProcessingTimeOfVessel>3</ProcessingTimeOfVessel>
    <ProcessingTimeOfVessel>6</ProcessingTimeOfVessel>
    <ProcessingTimeOfVessel>5</ProcessingTimeOfVessel>
    <ProcessingTimeOfVessel>5</ProcessingTimeOfVessel>
    <ProcessingTimeOfVessel>3</ProcessingTimeOfVessel>
    <ProcessingTimeOfVessel>5</ProcessingTimeOfVessel>
    <ProcessingTimeOfVessel>4</ProcessingTimeOfVessel>
    <ProcessingTimeOfVessel>4</ProcessingTimeOfVessel>
    <ProcessingTimeOfVessel>6</ProcessingTimeOfVessel>
    <ProcessingTimeOfVessel>5</ProcessingTimeOfVessel>
    <ProcessingTimeOfVessel>5</ProcessingTimeOfVessel>
    <ProcessingTimeOfVessel>4</ProcessingTimeOfVessel>
    <ProcessingTimeOfVessel>4</ProcessingTimeOfVessel>
    <ProcessingTimeOfVessel>6</ProcessingTimeOfVessel>
    <ProcessingTimeOfVessel>6</ProcessingTimeOfVessel>
    <ProcessingTimeOfVessel>6</ProcessingTimeOfVessel>
    <ProcessingTimeOfVessel>6</ProcessingTimeOfVessel>
    <ProcessingTimeOfVessel>5</ProcessingTimeOfVessel>
    <ProcessingTimeOfVessel>7</ProcessingTimeOfVessel>
    <ProcessingTimeOfVessel>5</ProcessingTimeOfVessel>
    <ProcessingTimeOfVessel>3</ProcessingTimeOfVessel>
    <ProcessingTimeOfVessel>6</ProcessingTimeOfVessel>
    <ProcessingTimeOfVessel>6</ProcessingTimeOfVessel>
    <ProcessingTimeOfVessel>4</ProcessingTimeOfVessel>
    <ProcessingTimeOfVessel>5</ProcessingTimeOfVessel>
    <ProcessingTimeOfVessel>6</ProcessingTimeOfVessel>
    <ProcessingTimeOfVessel>5</ProcessingTimeOfVessel>
    <ProcessingTimeOfVessel>7</ProcessingTimeOfVessel>
    <ProcessingTimeOfVessel>7</ProcessingTimeOfVessel>
    <ProcessingTimeOfVessel>4</ProcessingTimeOfVessel>
    <ProcessingTimeOfVessel>7</ProcessingTimeOfVessel>
    <ProcessingTimeOfVessel>3</ProcessingTimeOfVessel>
    <ProcessingTimeOfVessel>5</ProcessingTimeOfVessel>
    <ProcessingTimeOfVessel>3</ProcessingTimeOfVessel>
    <ProcessingTimeOfVessel>7</ProcessingTimeOfVessel>
    <ProcessingTimeOfVessel>3</ProcessingTimeOfVessel>
    <ProcessingTimeOfVessel>7</ProcessingTimeOfVessel>
    <ProcessingTimeOfVessel>6</ProcessingTimeOfVessel>
    <ProcessingTimeOfVessel>6</ProcessingTimeOfVessel>
    <ProcessingTimeOfVessel>7</ProcessingTimeOfVessel>
    <ProcessingTimeOfVessel>7</ProcessingTimeOfVessel>
    <ProcessingTimeOfVessel>4</ProcessingTimeOfVessel>
    <ProcessingTimeOfVessel>3</ProcessingTimeOfVessel>
    <ProcessingTimeOfVessel>6</ProcessingTimeOfVessel>
    <ProcessingTimeOfVessel>7</ProcessingTimeOfVessel>
    <ProcessingTimeOfVessel>5</ProcessingTimeOfVessel>
    <ProcessingTimeOfVessel>3</ProcessingTimeOfVessel>
    <ProcessingTimeOfVessel>6</ProcessingTimeOfVessel>
    <ProcessingTimeOfVessel>6</ProcessingTimeOfVessel>
    <ProcessingTimeOfVessel>7</ProcessingTimeOfVessel>
    <ProcessingTimeOfVessel>3</ProcessingTimeOfVessel>
    <ProcessingTimeOfVessel>3</ProcessingTimeOfVessel>
    <ProcessingTimeOfVessel>7</ProcessingTimeOfVessel>
    <ProcessingTimeOfVessel>5</ProcessingTimeOfVessel>
    <ProcessingTimeOfVessel>3</ProcessingTimeOfVessel>
    <ProcessingTimeOfVessel>6</ProcessingTimeOfVessel>
    <ProcessingTimeOfVessel>5</ProcessingTimeOfVessel>
    <ProcessingTimeOfVessel>7</ProcessingTimeOfVessel>
    <ProcessingTimeOfVessel>7</ProcessingTimeOfVessel>
    <ProcessingTimeOfVessel>7</ProcessingTimeOfVessel>
    <ProcessingTimeOfVessel>5</ProcessingTimeOfVessel>
    <ProcessingTimeOfVessel>7</ProcessingTimeOfVessel>
    <ProcessingTimeOfVessel>6</ProcessingTimeOfVessel>
    <ProcessingTimeOfVessel>6</ProcessingTimeOfVessel>
    <ProcessingTimeOfVessel>4</ProcessingTimeOfVessel>
    <ProcessingTimeOfVessel>3</ProcessingTimeOfVessel>
    <ProcessingTimeOfVessel>6</ProcessingTimeOfVessel>
    <ProcessingTimeOfVessel>6</ProcessingTimeOfVessel>
    <ProcessingTimeOfVessel>4</ProcessingTimeOfVessel>
    <ProcessingTimeOfVessel>6</ProcessingTimeOfVessel>
    <ProcessingTimeOfVessel>6</ProcessingTimeOfVessel>
    <ProcessingTimeOfVessel>6</ProcessingTimeOfVessel>
    <ProcessingTimeOfVessel>5</ProcessingTimeOfVessel>
    <ProcessingTimeOfVessel>5</ProcessingTimeOfVessel>
    <ArrivalTimeOfVessel>276</ArrivalTimeOfVessel>
    <ArrivalTimeOfVessel>290</ArrivalTimeOfVessel>
    <ArrivalTimeOfVessel>53</ArrivalTimeOfVessel>
    <ArrivalTimeOfVessel>216</ArrivalTimeOfVessel>
    <ArrivalTimeOfVessel>40</ArrivalTimeOfVessel>
    <ArrivalTimeOfVessel>336</ArrivalTimeOfVessel>
    <ArrivalTimeOfVessel>43</ArrivalTimeOfVessel>
    <ArrivalTimeOfVessel>45</ArrivalTimeOfVessel>
    <ArrivalTimeOfVessel>124</ArrivalTimeOfVessel>
    <ArrivalTimeOfVessel>257</ArrivalTimeOfVessel>
    <ArrivalTimeOfVessel>66</ArrivalTimeOfVessel>
    <ArrivalTimeOfVessel>26</ArrivalTimeOfVessel>
    <ArrivalTimeOfVessel>106</ArrivalTimeOfVessel>
    <ArrivalTimeOfVessel>138</ArrivalTimeOfVessel>
    <ArrivalTimeOfVessel>193</ArrivalTimeOfVessel>
    <ArrivalTimeOfVessel>83</ArrivalTimeOfVessel>
    <ArrivalTimeOfVessel>153</ArrivalTimeOfVessel>
    <ArrivalTimeOfVessel>352</ArrivalTimeOfVessel>
    <ArrivalTimeOfVessel>90</ArrivalTimeOfVessel>
    <ArrivalTimeOfVessel>114</ArrivalTimeOfVessel>
    <ArrivalTimeOfVessel>9</ArrivalTimeOfVessel>
    <ArrivalTimeOfVessel>164</ArrivalTimeOfVessel>
    <ArrivalTimeOfVessel>226</ArrivalTimeOfVessel>
    <ArrivalTimeOfVessel>317</ArrivalTimeOfVessel>
    <ArrivalTimeOfVessel>240</ArrivalTimeOfVessel>
    <ArrivalTimeOfVessel>282</ArrivalTimeOfVessel>
    <ArrivalTimeOfVessel>64</ArrivalTimeOfVessel>
    <ArrivalTimeOfVessel>217</ArrivalTimeOfVessel>
    <ArrivalTimeOfVessel>85</ArrivalTimeOfVessel>
    <ArrivalTimeOfVessel>257</ArrivalTimeOfVessel>
    <ArrivalTimeOfVessel>27</ArrivalTimeOfVessel>
    <ArrivalTimeOfVessel>49</ArrivalTimeOfVessel>
    <ArrivalTimeOfVessel>160</ArrivalTimeOfVessel>
    <ArrivalTimeOfVessel>140</ArrivalTimeOfVessel>
    <ArrivalTimeOfVessel>146</ArrivalTimeOfVessel>
    <ArrivalTimeOfVessel>353</ArrivalTimeOfVessel>
    <ArrivalTimeOfVessel>123</ArrivalTimeOfVessel>
    <ArrivalTimeOfVessel>154</ArrivalTimeOfVessel>
    <ArrivalTimeOfVessel>251</ArrivalTimeOfVessel>
    <ArrivalTimeOfVessel>45</ArrivalTimeOfVessel>
    <ArrivalTimeOfVessel>240</ArrivalTimeOfVessel>
    <ArrivalTimeOfVessel>307</ArrivalTimeOfVessel>
    <ArrivalTimeOfVessel>42</ArrivalTimeOfVessel>
    <ArrivalTimeOfVessel>107</ArrivalTimeOfVessel>
    <ArrivalTimeOfVessel>121</ArrivalTimeOfVessel>
    <ArrivalTimeOfVessel>89</ArrivalTimeOfVessel>
    <ArrivalTimeOfVessel>66</ArrivalTimeOfVessel>
    <ArrivalTimeOfVessel>249</ArrivalTimeOfVessel>
    <ArrivalTimeOfVessel>233</ArrivalTimeOfVessel>
    <ArrivalTimeOfVessel>112</ArrivalTimeOfVessel>
    <ArrivalTimeOfVessel>88</ArrivalTimeOfVessel>
    <ArrivalTimeOfVessel>314</ArrivalTimeOfVessel>
    <ArrivalTimeOfVessel>241</ArrivalTimeOfVessel>
    <ArrivalTimeOfVessel>83</ArrivalTimeOfVessel>
    <ArrivalTimeOfVessel>2</ArrivalTimeOfVessel>
    <ArrivalTimeOfVessel>153</ArrivalTimeOfVessel>
    <ArrivalTimeOfVessel>8</ArrivalTimeOfVessel>
    <ArrivalTimeOfVessel>216</ArrivalTimeOfVessel>
    <ArrivalTimeOfVessel>272</ArrivalTimeOfVessel>
    <ArrivalTimeOfVessel>193</ArrivalTimeOfVessel>
    <ArrivalTimeOfVessel>336</ArrivalTimeOfVessel>
    <ArrivalTimeOfVessel>161</ArrivalTimeOfVessel>
    <ArrivalTimeOfVessel>146</ArrivalTimeOfVessel>
    <ArrivalTimeOfVessel>195</ArrivalTimeOfVessel>
    <ArrivalTimeOfVessel>232</ArrivalTimeOfVessel>
    <ArrivalTimeOfVessel>258</ArrivalTimeOfVessel>
    <ArrivalTimeOfVessel>18</ArrivalTimeOfVessel>
    <ArrivalTimeOfVessel>274</ArrivalTimeOfVessel>
    <ArrivalTimeOfVessel>33</ArrivalTimeOfVessel>
    <ArrivalTimeOfVessel>243</ArrivalTimeOfVessel>
    <ArrivalTimeOfVessel>88</ArrivalTimeOfVessel>
    <ArrivalTimeOfVessel>130</ArrivalTimeOfVessel>
    <ArrivalTimeOfVessel>2</ArrivalTimeOfVessel>
    <ArrivalTimeOfVessel>153</ArrivalTimeOfVessel>
    <ArrivalTimeOfVessel>264</ArrivalTimeOfVessel>
    <ArrivalTimeOfVessel>242</ArrivalTimeOfVessel>
    <ArrivalTimeOfVessel>353</ArrivalTimeOfVessel>
    <ArrivalTimeOfVessel>148</ArrivalTimeOfVessel>
    <ArrivalTimeOfVessel>32</ArrivalTimeOfVessel>
    <ArrivalTimeOfVessel>176</ArrivalTimeOfVessel>
    <ArrivalTimeOfVessel>249</ArrivalTimeOfVessel>
    <ArrivalTimeOfVessel>307</ArrivalTimeOfVessel>
    <ArrivalTimeOfVessel>80</ArrivalTimeOfVessel>
    <ArrivalTimeOfVessel>208</ArrivalTimeOfVessel>
    <ArrivalTimeOfVessel>258</ArrivalTimeOfVessel>
    <ArrivalTimeOfVessel>208</ArrivalTimeOfVessel>
    <ArrivalTimeOfVessel>73</ArrivalTimeOfVessel>
    <ArrivalTimeOfVessel>18</ArrivalTimeOfVessel>
    <ArrivalTimeOfVessel>64</ArrivalTimeOfVessel>
    <ArrivalTimeOfVessel>177</ArrivalTimeOfVessel>
    <ArrivalTimeOfVessel>312</ArrivalTimeOfVessel>
    <ArrivalTimeOfVessel>75</ArrivalTimeOfVessel>
    <ArrivalTimeOfVessel>219</ArrivalTimeOfVessel>
    <ArrivalTimeOfVessel>18</ArrivalTimeOfVessel>
    <ArrivalTimeOfVessel>184</ArrivalTimeOfVessel>
    <ArrivalTimeOfVessel>104</ArrivalTimeOfVessel>
    <ArrivalTimeOfVessel>299</ArrivalTimeOfVessel>
    <ArrivalTimeOfVessel>59</ArrivalTimeOfVessel>
    <ArrivalTimeOfVessel>193</ArrivalTimeOfVessel>
    <ArrivalTimeOfVessel>275</ArrivalTimeOfVessel>
    <ArrivalTimeOfVessel>186</ArrivalTimeOfVessel>
    <ArrivalTimeOfVessel>170</ArrivalTimeOfVessel>
    <ArrivalTimeOfVessel>66</ArrivalTimeOfVessel>
    <ArrivalTimeOfVessel>24</ArrivalTimeOfVessel>
    <ArrivalTimeOfVessel>64</ArrivalTimeOfVessel>
    <ArrivalTimeOfVessel>112</ArrivalTimeOfVessel>
    <ArrivalTimeOfVessel>274</ArrivalTimeOfVessel>
    <ArrivalTimeOfVessel>192</ArrivalTimeOfVessel>
    <ArrivalTimeOfVessel>1</ArrivalTimeOfVessel>
    <ArrivalTimeOfVessel>250</ArrivalTimeOfVessel>
    <ArrivalTimeOfVessel>19</ArrivalTimeOfVessel>
    <ArrivalTimeOfVessel>43</ArrivalTimeOfVessel>
    <ArrivalTimeOfVessel>16</ArrivalTimeOfVessel>
    <ArrivalTimeOfVessel>42</ArrivalTimeOfVessel>
    <ArrivalTimeOfVessel>235</ArrivalTimeOfVessel>
    <ArrivalTimeOfVessel>346</ArrivalTimeOfVessel>
    <ArrivalTimeOfVessel>210</ArrivalTimeOfVessel>
    <ArrivalTimeOfVessel>73</ArrivalTimeOfVessel>
    <ArrivalTimeOfVessel>51</ArrivalTimeOfVessel>
    <ArrivalTimeOfVessel>33</ArrivalTimeOfVessel>
    <RequestedDep_Time>283</RequestedDep_Time>
    <RequestedDep_Time>298</RequestedDep_Time>
    <RequestedDep_Time>58</RequestedDep_Time>
    <RequestedDep_Time>225</RequestedDep_Time>
    <RequestedDep_Time>45</RequestedDep_Time>
    <RequestedDep_Time>345</RequestedDep_Time>
    <RequestedDep_Time>48</RequestedDep_Time>
    <RequestedDep_Time>52</RequestedDep_Time>
    <RequestedDep_Time>128</RequestedDep_Time>
    <RequestedDep_Time>265</RequestedDep_Time>
    <RequestedDep_Time>72</RequestedDep_Time>
    <RequestedDep_Time>35</RequestedDep_Time>
    <RequestedDep_Time>113</RequestedDep_Time>
    <RequestedDep_Time>146</RequestedDep_Time>
    <RequestedDep_Time>202</RequestedDep_Time>
    <RequestedDep_Time>88</RequestedDep_Time>
    <RequestedDep_Time>161</RequestedDep_Time>
    <RequestedDep_Time>359</RequestedDep_Time>
    <RequestedDep_Time>98</RequestedDep_Time>
    <RequestedDep_Time>120</RequestedDep_Time>
    <RequestedDep_Time>19</RequestedDep_Time>
    <RequestedDep_Time>170</RequestedDep_Time>
    <RequestedDep_Time>232</RequestedDep_Time>
    <RequestedDep_Time>323</RequestedDep_Time>
    <RequestedDep_Time>247</RequestedDep_Time>
    <RequestedDep_Time>291</RequestedDep_Time>
    <RequestedDep_Time>73</RequestedDep_Time>
    <RequestedDep_Time>228</RequestedDep_Time>
    <RequestedDep_Time>88</RequestedDep_Time>
    <RequestedDep_Time>266</RequestedDep_Time>
    <RequestedDep_Time>30</RequestedDep_Time>
    <RequestedDep_Time>57</RequestedDep_Time>
    <RequestedDep_Time>171</RequestedDep_Time>
    <RequestedDep_Time>147</RequestedDep_Time>
    <RequestedDep_Time>154</RequestedDep_Time>
    <RequestedDep_Time>356</RequestedDep_Time>
    <RequestedDep_Time>132</RequestedDep_Time>
    <RequestedDep_Time>162</RequestedDep_Time>
    <RequestedDep_Time>257</RequestedDep_Time>
    <RequestedDep_Time>48</RequestedDep_Time>
    <RequestedDep_Time>248</RequestedDep_Time>
    <RequestedDep_Time>311</RequestedDep_Time>
    <RequestedDep_Time>48</RequestedDep_Time>
    <RequestedDep_Time>112</RequestedDep_Time>
    <RequestedDep_Time>127</RequestedDep_Time>
    <RequestedDep_Time>96</RequestedDep_Time>
    <RequestedDep_Time>69</RequestedDep_Time>
    <RequestedDep_Time>255</RequestedDep_Time>
    <RequestedDep_Time>242</RequestedDep_Time>
    <RequestedDep_Time>120</RequestedDep_Time>
    <RequestedDep_Time>92</RequestedDep_Time>
    <RequestedDep_Time>323</RequestedDep_Time>
    <RequestedDep_Time>248</RequestedDep_Time>
    <RequestedDep_Time>91</RequestedDep_Time>
    <RequestedDep_Time>9</RequestedDep_Time>
    <RequestedDep_Time>161</RequestedDep_Time>
    <RequestedDep_Time>16</RequestedDep_Time>
    <RequestedDep_Time>223</RequestedDep_Time>
    <RequestedDep_Time>277</RequestedDep_Time>
    <RequestedDep_Time>202</RequestedDep_Time>
    <RequestedDep_Time>345</RequestedDep_Time>
    <RequestedDep_Time>170</RequestedDep_Time>
    <RequestedDep_Time>156</RequestedDep_Time>
    <RequestedDep_Time>201</RequestedDep_Time>
    <RequestedDep_Time>242</RequestedDep_Time>
    <RequestedDep_Time>267</RequestedDep_Time>
    <RequestedDep_Time>23</RequestedDep_Time>
    <RequestedDep_Time>284</RequestedDep_Time>
    <RequestedDep_Time>41</RequestedDep_Time>
    <RequestedDep_Time>249</RequestedDep_Time>
    <RequestedDep_Time>96</RequestedDep_Time>
    <RequestedDep_Time>137</RequestedDep_Time>
    <RequestedDep_Time>9</RequestedDep_Time>
    <RequestedDep_Time>161</RequestedDep_Time>
    <RequestedDep_Time>272</RequestedDep_Time>
    <RequestedDep_Time>250</RequestedDep_Time>
    <RequestedDep_Time>360</RequestedDep_Time>
    <RequestedDep_Time>155</RequestedDep_Time>
    <RequestedDep_Time>37</RequestedDep_Time>
    <RequestedDep_Time>179</RequestedDep_Time>
    <RequestedDep_Time>260</RequestedDep_Time>
    <RequestedDep_Time>314</RequestedDep_Time>
    <RequestedDep_Time>91</RequestedDep_Time>
    <RequestedDep_Time>217</RequestedDep_Time>
    <RequestedDep_Time>268</RequestedDep_Time>
    <RequestedDep_Time>215</RequestedDep_Time>
    <RequestedDep_Time>83</RequestedDep_Time>
    <RequestedDep_Time>22</RequestedDep_Time>
    <RequestedDep_Time>70</RequestedDep_Time>
    <RequestedDep_Time>185</RequestedDep_Time>
    <RequestedDep_Time>320</RequestedDep_Time>
    <RequestedDep_Time>80</RequestedDep_Time>
    <RequestedDep_Time>222</RequestedDep_Time>
    <RequestedDep_Time>28</RequestedDep_Time>
    <RequestedDep_Time>191</RequestedDep_Time>
    <RequestedDep_Time>112</RequestedDep_Time>
    <RequestedDep_Time>306</RequestedDep_Time>
    <RequestedDep_Time>63</RequestedDep_Time>
    <RequestedDep_Time>204</RequestedDep_Time>
    <RequestedDep_Time>280</RequestedDep_Time>
    <RequestedDep_Time>189</RequestedDep_Time>
    <RequestedDep_Time>176</RequestedDep_Time>
    <RequestedDep_Time>72</RequestedDep_Time>
    <RequestedDep_Time>31</RequestedDep_Time>
    <RequestedDep_Time>72</RequestedDep_Time>
    <RequestedDep_Time>119</RequestedDep_Time>
    <RequestedDep_Time>279</RequestedDep_Time>
    <RequestedDep_Time>203</RequestedDep_Time>
    <RequestedDep_Time>10</RequestedDep_Time>
    <RequestedDep_Time>257</RequestedDep_Time>
    <RequestedDep_Time>24</RequestedDep_Time>
    <RequestedDep_Time>48</RequestedDep_Time>
    <RequestedDep_Time>22</RequestedDep_Time>
    <RequestedDep_Time>48</RequestedDep_Time>
    <RequestedDep_Time>241</RequestedDep_Time>
    <RequestedDep_Time>352</RequestedDep_Time>
    <RequestedDep_Time>217</RequestedDep_Time>
    <RequestedDep_Time>81</RequestedDep_Time>
    <RequestedDep_Time>56</RequestedDep_Time>
    <RequestedDep_Time>38</RequestedDep_Time>
    <LowestCostBerthingPos_>3473</LowestCostBerthingPos_>
    <LowestCostBerthingPos_>2924</LowestCostBerthingPos_>
    <LowestCostBerthingPos_>553</LowestCostBerthingPos_>
    <LowestCostBerthingPos_>3142</LowestCostBerthingPos_>
    <LowestCostBerthingPos_>2160</LowestCostBerthingPos_>
    <LowestCostBerthingPos_>153</LowestCostBerthingPos_>
    <LowestCostBerthingPos_>1308</LowestCostBerthingPos_>
    <LowestCostBerthingPos_>1651</LowestCostBerthingPos_>
    <LowestCostBerthingPos_>3485</LowestCostBerthingPos_>
    <LowestCostBerthingPos_>3481</LowestCostBerthingPos_>
    <LowestCostBerthingPos_>320</LowestCostBerthingPos_>
    <LowestCostBerthingPos_>3211</LowestCostBerthingPos_>
    <LowestCostBerthingPos_>3468</LowestCostBerthingPos_>
    <LowestCostBerthingPos_>1817</LowestCostBerthingPos_>
    <LowestCostBerthingPos_>2663</LowestCostBerthingPos_>
    <LowestCostBerthingPos_>643</LowestCostBerthingPos_>
    <LowestCostBerthingPos_>855</LowestCostBerthingPos_>
    <LowestCostBerthingPos_>3368</LowestCostBerthingPos_>
    <LowestCostBerthingPos_>2334</LowestCostBerthingPos_>
    <LowestCostBerthingPos_>3220</LowestCostBerthingPos_>
    <LowestCostBerthingPos_>2552</LowestCostBerthingPos_>
    <LowestCostBerthingPos_>695</LowestCostBerthingPos_>
    <LowestCostBerthingPos_>2929</LowestCostBerthingPos_>
    <LowestCostBerthingPos_>3377</LowestCostBerthingPos_>
    <LowestCostBerthingPos_>2691</LowestCostBerthingPos_>
    <LowestCostBerthingPos_>2717</LowestCostBerthingPos_>
    <LowestCostBerthingPos_>2476</LowestCostBerthingPos_>
    <LowestCostBerthingPos_>1171</LowestCostBerthingPos_>
    <LowestCostBerthingPos_>2679</LowestCostBerthingPos_>
    <LowestCostBerthingPos_>349</LowestCostBerthingPos_>
    <LowestCostBerthingPos_>2730</LowestCostBerthingPos_>
    <LowestCostBerthingPos_>596</LowestCostBerthingPos_>
    <LowestCostBerthingPos_>1366</LowestCostBerthingPos_>
    <LowestCostBerthingPos_>678</LowestCostBerthingPos_>
    <LowestCostBerthingPos_>344</LowestCostBerthingPos_>
    <LowestCostBerthingPos_>3365</LowestCostBerthingPos_>
    <LowestCostBerthingPos_>2522</LowestCostBerthingPos_>
    <LowestCostBerthingPos_>1318</LowestCostBerthingPos_>
    <LowestCostBerthingPos_>3457</LowestCostBerthingPos_>
    <LowestCostBerthingPos_>108</LowestCostBerthingPos_>
    <LowestCostBerthingPos_>1070</LowestCostBerthingPos_>
    <LowestCostBerthingPos_>1312</LowestCostBerthingPos_>
    <LowestCostBerthingPos_>2287</LowestCostBerthingPos_>
    <LowestCostBerthingPos_>2680</LowestCostBerthingPos_>
    <LowestCostBerthingPos_>540</LowestCostBerthingPos_>
    <LowestCostBerthingPos_>2026</LowestCostBerthingPos_>
    <LowestCostBerthingPos_>2048</LowestCostBerthingPos_>
    <LowestCostBerthingPos_>1794</LowestCostBerthingPos_>
    <LowestCostBerthingPos_>2702</LowestCostBerthingPos_>
    <LowestCostBerthingPos_>2684</LowestCostBerthingPos_>
    <LowestCostBerthingPos_>1301</LowestCostBerthingPos_>
    <LowestCostBerthingPos_>2288</LowestCostBerthingPos_>
    <LowestCostBerthingPos_>2496</LowestCostBerthingPos_>
    <LowestCostBerthingPos_>715</LowestCostBerthingPos_>
    <LowestCostBerthingPos_>562</LowestCostBerthingPos_>
    <LowestCostBerthingPos_>2166</LowestCostBerthingPos_>
    <LowestCostBerthingPos_>2875</LowestCostBerthingPos_>
    <LowestCostBerthingPos_>1124</LowestCostBerthingPos_>
    <LowestCostBerthingPos_>2100</LowestCostBerthingPos_>
    <LowestCostBerthingPos_>899</LowestCostBerthingPos_>
    <LowestCostBerthingPos_>2722</LowestCostBerthingPos_>
    <LowestCostBerthingPos_>1426</LowestCostBerthingPos_>
    <LowestCostBerthingPos_>1865</LowestCostBerthingPos_>
    <LowestCostBerthingPos_>2692</LowestCostBerthingPos_>
    <LowestCostBerthingPos_>3129</LowestCostBerthingPos_>
    <LowestCostBerthingPos_>3448</LowestCostBerthingPos_>
    <LowestCostBerthingPos_>1600</LowestCostBerthingPos_>
    <LowestCostBerthingPos_>43</LowestCostBerthingPos_>
    <LowestCostBerthingPos_>418</LowestCostBerthingPos_>
    <LowestCostBerthingPos_>1362</LowestCostBerthingPos_>
    <LowestCostBerthingPos_>3505</LowestCostBerthingPos_>
    <LowestCostBerthingPos_>1317</LowestCostBerthingPos_>
    <LowestCostBerthingPos_>2491</LowestCostBerthingPos_>
    <LowestCostBerthingPos_>908</LowestCostBerthingPos_>
    <LowestCostBerthingPos_>3183</LowestCostBerthingPos_>
    <LowestCostBerthingPos_>1067</LowestCostBerthingPos_>
    <LowestCostBerthingPos_>1323</LowestCostBerthingPos_>
    <LowestCostBerthingPos_>1317</LowestCostBerthingPos_>
    <LowestCostBerthingPos_>2041</LowestCostBerthingPos_>
    <LowestCostBerthingPos_>2103</LowestCostBerthingPos_>
    <LowestCostBerthingPos_>1066</LowestCostBerthingPos_>
    <LowestCostBerthingPos_>3386</LowestCostBerthingPos_>
    <LowestCostBerthingPos_>2155</LowestCostBerthingPos_>
    <LowestCostBerthingPos_>1571</LowestCostBerthingPos_>
    <LowestCostBerthingPos_>3373</LowestCostBerthingPos_>
    <LowestCostBerthingPos_>1325</LowestCostBerthingPos_>
    <LowestCostBerthingPos_>2658</LowestCostBerthingPos_>
    <LowestCostBerthingPos_>2652</LowestCostBerthingPos_>
    <LowestCostBerthingPos_>1333</LowestCostBerthingPos_>
    <LowestCostBerthingPos_>1819</LowestCostBerthingPos_>
    <LowestCostBerthingPos_>617</LowestCostBerthingPos_>
    <LowestCostBerthingPos_>660</LowestCostBerthingPos_>
    <LowestCostBerthingPos_>2079</LowestCostBerthingPos_>
    <LowestCostBerthingPos_>2461</LowestCostBerthingPos_>
    <LowestCostBerthingPos_>3165</LowestCostBerthingPos_>
    <LowestCostBerthingPos_>345</LowestCostBerthingPos_>
    <LowestCostBerthingPos_>2026</LowestCostBerthingPos_>
    <LowestCostBerthingPos_>1881</LowestCostBerthingPos_>
    <LowestCostBerthingPos_>582</LowestCostBerthingPos_>
    <LowestCostBerthingPos_>1101</LowestCostBerthingPos_>
    <LowestCostBerthingPos_>539</LowestCostBerthingPos_>
    <LowestCostBerthingPos_>2277</LowestCostBerthingPos_>
    <LowestCostBerthingPos_>846</LowestCostBerthingPos_>
    <LowestCostBerthingPos_>2078</LowestCostBerthingPos_>
    <LowestCostBerthingPos_>399</LowestCostBerthingPos_>
    <LowestCostBerthingPos_>2173</LowestCostBerthingPos_>
    <LowestCostBerthingPos_>1338</LowestCostBerthingPos_>
    <LowestCostBerthingPos_>1834</LowestCostBerthingPos_>
    <LowestCostBerthingPos_>2726</LowestCostBerthingPos_>
    <LowestCostBerthingPos_>2750</LowestCostBerthingPos_>
    <LowestCostBerthingPos_>1634</LowestCostBerthingPos_>
    <LowestCostBerthingPos_>69</LowestCostBerthingPos_>
    <LowestCostBerthingPos_>1319</LowestCostBerthingPos_>
    <LowestCostBerthingPos_>2922</LowestCostBerthingPos_>
    <LowestCostBerthingPos_>607</LowestCostBerthingPos_>
    <LowestCostBerthingPos_>3465</LowestCostBerthingPos_>
    <LowestCostBerthingPos_>2039</LowestCostBerthingPos_>
    <LowestCostBerthingPos_>3356</LowestCostBerthingPos_>
    <LowestCostBerthingPos_>634</LowestCostBerthingPos_>
    <LowestCostBerthingPos_>2074</LowestCostBerthingPos_>
</struct>
